pandasplit/__init__.py
pandasplit-0.1.dist-info/METADATA
pandasplit-0.1.dist-info/RECORD
pandasplit-0.1.dist-info/WHEEL
pandasplit-0.1.dist-info/top_level.txt
