Metadata-Version: 2.1
Name: pandasplit
Version: 0.1
Summary: split pandas data into groups
Home-page: http://github.com/passionke/pandas-split
Author: passionke
Author-email: kejiqing@gmail.com
License: MIT
Platform: UNKNOWN
